MANIFEST.in
README.md
setup.py
dash_audio_components/DashAudioComponents.py
dash_audio_components/__init__.py
dash_audio_components/_imports_.py
dash_audio_components/dash_audio_components.dev.js
dash_audio_components/dash_audio_components.min.js
dash_audio_components/metadata.json
dash_audio_components/package.json
dash_audio_components.egg-info/PKG-INFO
dash_audio_components.egg-info/SOURCES.txt
dash_audio_components.egg-info/dependency_links.txt
dash_audio_components.egg-info/top_level.txt