Metadata-Version: 1.0
Name: dash-audio-components
Version: 1.1.0
Summary: Dash component to play audio files
Home-page: UNKNOWN
Author: Lukasz Tracewski lukasz.tracewski@outlook.com
Author-email: UNKNOWN
License: MIT
Platform: UNKNOWN
